<?xml version="1.0" ?><annotation>
	<folder>PictureData_0924_20_1-368</folder>
	<filename>0924_20_346.jpg</filename>
	<path>C:\Users\LXU7EC\Documents\PictureData\PictureData_0924_20_1-368\0924_20_346.jpg</path>
	<source>
		<database>Unknown</database>
	</source>
	<size>
		<width>1280</width>
		<height>720</height>
		<depth>3</depth>
	</size>
	<segmented>0</segmented>
	<object>
		<name>truck</name>
		<pose>Unspecified</pose>
		<truncated>1</truncated>
		<difficult>0</difficult>
		<bndbox>
			<xmin>188</xmin>
			<ymin>403</ymin>
			<xmax>652</xmax>
			<ymax>720</ymax>
		</bndbox>
	</object>
	<object>
		<name>excavator</name>
		<pose>Unspecified</pose>
		<truncated>1</truncated>
		<difficult>0</difficult>
		<bndbox>
			<xmin>191</xmin>
			<ymin>1</ymin>
			<xmax>746</xmax>
			<ymax>628</ymax>
		</bndbox>
	</object>
	<object>
		<name>excavator</name>
		<pose>Unspecified</pose>
		<truncated>1</truncated>
		<difficult>0</difficult>
		<bndbox>
			<xmin>381</xmin>
			<ymin>1</ymin>
			<xmax>944</xmax>
			<ymax>545</ymax>
		</bndbox>
	</object>
	<object>
		<name>excavator</name>
		<pose>Unspecified</pose>
		<truncated>0</truncated>
		<difficult>0</difficult>
		<bndbox>
			<xmin>348</xmin>
			<ymin>34</ymin>
			<xmax>834</xmax>
			<ymax>330</ymax>
		</bndbox>
	</object>
	<object>
		<name>excavator</name>
		<pose>Unspecified</pose>
		<truncated>0</truncated>
		<difficult>0</difficult>
		<bndbox>
			<xmin>767</xmin>
			<ymin>123</ymin>
			<xmax>1074</xmax>
			<ymax>313</ymax>
		</bndbox>
	</object>
	<object>
		<name>truck</name>
		<pose>Unspecified</pose>
		<truncated>1</truncated>
		<difficult>0</difficult>
		<bndbox>
			<xmin>1143</xmin>
			<ymin>169</ymin>
			<xmax>1280</xmax>
			<ymax>331</ymax>
		</bndbox>
	</object>
</annotation>