<?xml version="1.0" ?><annotation>
	<folder>PictureData_0924_13_521-1040</folder>
	<filename>0924_13_639.jpg</filename>
	<path>C:\Users\LXU7EC\Documents\PictureData\PictureData_0924_13_521-1040\0924_13_639.jpg</path>
	<source>
		<database>Unknown</database>
	</source>
	<size>
		<width>480</width>
		<height>360</height>
		<depth>3</depth>
	</size>
	<segmented>0</segmented>
	<object>
		<name>truck</name>
		<pose>Unspecified</pose>
		<truncated>0</truncated>
		<difficult>0</difficult>
		<bndbox>
			<xmin>382</xmin>
			<ymin>155</ymin>
			<xmax>447</xmax>
			<ymax>181</ymax>
		</bndbox>
	</object>
	<object>
		<name>truck</name>
		<pose>Unspecified</pose>
		<truncated>1</truncated>
		<difficult>0</difficult>
		<bndbox>
			<xmin>1</xmin>
			<ymin>192</ymin>
			<xmax>196</xmax>
			<ymax>280</ymax>
		</bndbox>
	</object>
	<object>
		<name>excavator</name>
		<pose>Unspecified</pose>
		<truncated>0</truncated>
		<difficult>0</difficult>
		<bndbox>
			<xmin>149</xmin>
			<ymin>92</ymin>
			<xmax>400</xmax>
			<ymax>295</ymax>
		</bndbox>
	</object>
</annotation>