<?xml version="1.0" ?><annotation>
	<folder>PictureData_0924_13_521-1040</folder>
	<filename>0924_13_947.jpg</filename>
	<path>C:\Users\LXU7EC\Documents\PictureData\PictureData_0924_13_521-1040\0924_13_947.jpg</path>
	<source>
		<database>Unknown</database>
	</source>
	<size>
		<width>480</width>
		<height>360</height>
		<depth>3</depth>
	</size>
	<segmented>0</segmented>
	<object>
		<name>truck</name>
		<pose>Unspecified</pose>
		<truncated>0</truncated>
		<difficult>0</difficult>
		<bndbox>
			<xmin>396</xmin>
			<ymin>186</ymin>
			<xmax>426</xmax>
			<ymax>205</ymax>
		</bndbox>
	</object>
	<object>
		<name>excavator</name>
		<pose>Unspecified</pose>
		<truncated>0</truncated>
		<difficult>0</difficult>
		<bndbox>
			<xmin>122</xmin>
			<ymin>85</ymin>
			<xmax>401</xmax>
			<ymax>221</ymax>
		</bndbox>
	</object>
	<object>
		<name>truck</name>
		<pose>Unspecified</pose>
		<truncated>0</truncated>
		<difficult>0</difficult>
		<bndbox>
			<xmin>79</xmin>
			<ymin>157</ymin>
			<xmax>279</xmax>
			<ymax>282</ymax>
		</bndbox>
	</object>
</annotation>