<?xml version="1.0" ?><annotation>
	<folder>PictureData_0924_20_1105-1472</folder>
	<filename>0924_20_1298.jpg</filename>
	<path>C:\Users\LXU7EC\Documents\PictureData\PictureData_0924_20_1105-1472\0924_20_1298.jpg</path>
	<source>
		<database>Unknown</database>
	</source>
	<size>
		<width>1280</width>
		<height>720</height>
		<depth>3</depth>
	</size>
	<segmented>0</segmented>
	<object>
		<name>truck</name>
		<pose>Unspecified</pose>
		<truncated>0</truncated>
		<difficult>0</difficult>
		<bndbox>
			<xmin>654</xmin>
			<ymin>330</ymin>
			<xmax>726</xmax>
			<ymax>388</ymax>
		</bndbox>
	</object>
	<object>
		<name>excavator</name>
		<pose>Unspecified</pose>
		<truncated>0</truncated>
		<difficult>0</difficult>
		<bndbox>
			<xmin>638</xmin>
			<ymin>271</ymin>
			<xmax>758</xmax>
			<ymax>359</ymax>
		</bndbox>
	</object>
	<object>
		<name>excavator</name>
		<pose>Unspecified</pose>
		<truncated>0</truncated>
		<difficult>0</difficult>
		<bndbox>
			<xmin>675</xmin>
			<ymin>282</ymin>
			<xmax>736</xmax>
			<ymax>348</ymax>
		</bndbox>
	</object>
	<object>
		<name>excavator</name>
		<pose>Unspecified</pose>
		<truncated>0</truncated>
		<difficult>0</difficult>
		<bndbox>
			<xmin>730</xmin>
			<ymin>289</ymin>
			<xmax>768</xmax>
			<ymax>328</ymax>
		</bndbox>
	</object>
	<object>
		<name>truck</name>
		<pose>Unspecified</pose>
		<truncated>0</truncated>
		<difficult>0</difficult>
		<bndbox>
			<xmin>758</xmin>
			<ymin>313</ymin>
			<xmax>778</xmax>
			<ymax>336</ymax>
		</bndbox>
	</object>
	<object>
		<name>truck</name>
		<pose>Unspecified</pose>
		<truncated>0</truncated>
		<difficult>0</difficult>
		<bndbox>
			<xmin>896</xmin>
			<ymin>338</ymin>
			<xmax>993</xmax>
			<ymax>437</ymax>
		</bndbox>
	</object>
</annotation>